genice_rdf/__init__.py
genice_rdf/formats/_RDF.py
genice_rdf/formats/__init__.py
genice_rdf-0.3.3.dist-info/METADATA
genice_rdf-0.3.3.dist-info/WHEEL
genice_rdf-0.3.3.dist-info/entry_points.txt
genice_rdf-0.3.3.dist-info/top_level.txt
genice_rdf-0.3.3.dist-info/RECORD
