Metadata-Version: 2.1
Name: genice-rdf
Version: 0.3.3
Summary: RDF format plugin for GenIce.
Home-page: https://github.com/vitroid/genice-rdf/
Author: Masakazu Matsumoto
Author-email: vitroid@gmail.com
License: MIT
Keywords: genice,RDF
Platform: UNKNOWN
Classifier: Development Status :: 4 - Beta
Classifier: Intended Audience :: Developers
Classifier: Programming Language :: Python
Classifier: Programming Language :: Python :: 3.5
Requires-Dist: PairList (>=0.2.3)
Requires-Dist: GenIce (<2.0)
